{
	"-": {
		"strokes": [[ { "x": 0, "y": 0 }, {"x": 200,"y": 0 } ]]
	},
	"0": {
		"strokes": [[ {
			"x": 100,
			"y": 0
		}, {
			"x": 0,
			"y": 150
		}, {
			"x": 100,
			"y": 300
		}, {
			"x": 200,
			"y": 100
		}, {
			"x": 100,
			"y": 0
		} ]]
	},
	"1": {
		"strokes": [[ {"x": 0,"y": 0}, {"x": 0,"y": 200} ]]
	},
	"2": {
		"strokes": [[{
			"x": 0,
			"y": 0
		}, {
			"x": 150,
			"y": 0
		}, {
			"x": 0,
			"y": 250
		}, {
			"x": 200,
			"y": 250
		} ]]
	},
	"3":{
		"strokes":[[{"x":20,"y":50},{"x":25,"y":42},{"x":53,"y":22},{"x":75,"y":10},{"x":100,"y":1},{"x":153,"y":0},{"x":171,"y":7},{"x":181,"y":15},{"x":187,"y":23},{"x":194,"y":29},{"x":204,"y":47},{"x":204,"y":84},{"x":198,"y":91},{"x":180,"y":104},{"x":178,"y":104},{"x":170,"y":112},{"x":162,"y":124},{"x":138,"y":147},{"x":124,"y":167},{"x":124,"y":170},{"x":124,"y":166},{"x":142,"y":158},{"x":191,"y":158},{"x":220,"y":181},{"x":229,"y":192},{"x":234,"y":205},{"x":234,"y":249},{"x":233,"y":253},{"x":216,"y":279},{"x":204,"y":291},{"x":190,"y":300},{"x":163,"y":310},{"x":130,"y":316},{"x":114,"y":317},{"x":70,"y":316},{"x":38,"y":307},{"x":25,"y":299},{"x":14,"y":287},{"x":6,"y":275},{"x":0,"y":256},{"x":0,"y":251}]]
	},
	"4":{
		"strokes":[
			[{"x":100,"y":0},{"x":0,"y":100},{"x":200,"y":100}],
			[{"x":100,"y":0},{"x":100,"y":200}]
		]
	},
	"6": {
		"strokes": [[{"x":112,"y":0},{"x":95,"y":0},{"x":57,"y":29},{"x":39,"y":46},{"x":29,"y":57},{"x":21,"y":70},{"x":5,"y":103},{"x":0,"y":148},{"x":0,"y":237},{"x":6,"y":242},{"x":53,"y":270},{"x":62,"y":274},{"x":80,"y":278},{"x":120,"y":278},{"x":137,"y":271},{"x":153,"y":260},{"x":159,"y":249},{"x":160,"y":244},{"x":160,"y":216},{"x":157,"y":201},{"x":146,"y":181},{"x":137,"y":171},{"x":120,"y":160},{"x":101,"y":151},{"x":73,"y":141},{"x":39,"y":141},{"x":8,"y":150},{"x":3,"y":150}]]
	},
	"8": {
		"strokes":[[{"x":77,"y":82},{"x":80,"y":82},{"x":88,"y":78},{"x":98,"y":64},{"x":102,"y":55},{"x":104,"y":49},{"x":104,"y":27},{"x":101,"y":23},{"x":94,"y":16},{"x":81,"y":9},{"x":60,"y":2},{"x":44,"y":0},{"x":16,"y":1},{"x":7,"y":15},{"x":0,"y":32},{"x":0,"y":97},{"x":18,"y":112},{"x":45,"y":128},{"x":70,"y":136},{"x":101,"y":151},{"x":122,"y":169},{"x":133,"y":183},{"x":140,"y":197},{"x":140,"y":230},{"x":138,"y":234},{"x":130,"y":240},{"x":115,"y":246},{"x":48,"y":246},{"x":44,"y":242},{"x":39,"y":232},{"x":38,"y":183},{"x":81,"y":132},{"x":92,"y":114},{"x":99,"y":99},{"x":103,"y":95},{"x":104,"y":89}]]
	},
	"9":{
		"strokes":[[{"x":138,"y":9},{"x":115,"y":2},{"x":78,"y":0},{"x":47,"y":0},{"x":31,"y":5},{"x":10,"y":26},{"x":4,"y":38},{"x":0,"y":57},{"x":0,"y":90},{"x":5,"y":96},{"x":15,"y":103},{"x":24,"y":106},{"x":38,"y":109},{"x":70,"y":109},{"x":75,"y":107},{"x":103,"y":90},{"x":112,"y":82},{"x":119,"y":73},{"x":126,"y":58},{"x":130,"y":34},{"x":132,"y":31},{"x":132,"y":23},{"x":132,"y":41},{"x":144,"y":178},{"x":143,"y":293}]]
	},
	"(": {
		"strokes": [[ {
			"x": 150,
			"y": 0
		}, {
			"x": 0,
			"y": 200
		}, {
			"x": 150,
			"y": 400
		} ]]
	},
	")": {
		"strokes": [[ {
			"x": 0,
			"y": 0
		}, {
			"x": 100,
			"y": 200
		}, {
			"x": 0,
			"y": 400
		} ]]
	},
	"7": {
		"strokes":[ [ {
			"x": 0,
			"y": 0
		}, {
			"x": 200,
			"y": 0
		}, {
			"x": 100,
			"y": 300
		} ]]
	},
	"v": {
		"strokes": [[ {
			"x": 0,
			"y": 0
		}, {
			"x": 100,
			"y": 200
		}, {
			"x": 200,
			"y": 0
		} ]]
    },
    "ட": {
        "strokes":[
            [{"x":0,"y":0},{"x":5,"y":112},{"x":5,"y":185},{"x":75,"y":185},{"x":89,"y":186},{"x":99,"y":189},{"x":206,"y":189}]
        ]
    },
    "ப": {
        "strokes":[
            [{"x":0,"y":13},{"x":0,"y":198},{"x":43,"y":198},{"x":74,"y":192},{"x":122,"y":188},{"x":224,"y":188},{"x":230,"y":191},{"x":237,"y":191},{"x":238,"y":102},{"x":241,"y":55},{"x":244,"y":40},{"x":244,"y":0}]
        ]
    },
    "அ": {
        "strokes":[
            [{"x":26,"y":39},{"x":47,"y":38},{"x":55,"y":43},{"x":63,"y":55},{"x":63,"y":80},{"x":56,"y":88},{"x":49,"y":93},{"x":41,"y":96},{"x":16,"y":97},{"x":14,"y":95},{"x":5,"y":76},{"x":5,"y":47},{"x":23,"y":29},{"x":41,"y":16},{"x":71,"y":8},{"x":94,"y":8},{"x":99,"y":10},{"x":120,"y":24},{"x":127,"y":31},{"x":133,"y":41},{"x":138,"y":62},{"x":138,"y":105},{"x":132,"y":119},{"x":123,"y":132},{"x":116,"y":139},{"x":94,"y":156},{"x":71,"y":170},{"x":53,"y":177},{"x":43,"y":179},{"x":24,"y":181},{"x":4,"y":181},{"x":0,"y":161},{"x":0,"y":134},{"x":10,"y":127},{"x":25,"y":120},{"x":56,"y":113},{"x":183,"y":113},{"x":188,"y":101},{"x":195,"y":60},{"x":195,"y":32},{"x":199,"y":0},{"x":199,"y":52},{"x":180,"y":124},{"x":178,"y":142},{"x":178,"y":188},{"x":176,"y":193}]
        ]
    },
    "ஸ":{
		"strokes":[
            [{"x":0,"y":184},{"x":1,"y":92},{"x":5,"y":83},{"x":11,"y":76},{"x":24,"y":68},{"x":38,"y":68},{"x":47,"y":75},{"x":57,"y":89},{"x":84,"y":135},{"x":91,"y":160},{"x":95,"y":185},{"x":100,"y":145},{"x":113,"y":110},{"x":134,"y":77},{"x":144,"y":64},{"x":151,"y":58},{"x":162,"y":58},{"x":171,"y":73},{"x":184,"y":104},{"x":195,"y":122},{"x":203,"y":132},{"x":237,"y":171},{"x":253,"y":187},{"x":258,"y":190},{"x":274,"y":189},{"x":286,"y":180},{"x":290,"y":166},{"x":291,"y":66},{"x":289,"y":34},{"x":283,"y":8},{"x":283,"y":0}]
        ]
	}
}
